damakye_lda/__init__.py
damakye_lda/lda.py
damakye_lda/utils.py
damakye_lda-0.1.0.dist-info/METADATA
damakye_lda-0.1.0.dist-info/WHEEL
damakye_lda-0.1.0.dist-info/top_level.txt
damakye_lda-0.1.0.dist-info/RECORD
