Metadata-Version: 2.1
Name: damakye-lda
Version: 0.1.0
Summary: A Python package for Linear Discriminant Analysis (LDA)
Home-page: https://github.com/DanielAgyekumAmakyeGh/damakye_lda
Author: Daniel Agyekum Amakye 
Author-email: your.janetobosuayaa@gmail.com
Classifier: Programming Language :: Python :: 3
Classifier: License :: OSI Approved :: MIT License
Classifier: Operating System :: OS Independent
Requires-Python: >=3.6
Requires-Dist: numpy>=1.18.0
Requires-Dist: pandas>=1.0.0
Requires-Dist: scikit-learn>=0.24.0
